{
  "updated": "2026-06-04 23:59 CEST",
  "today": {
    "weekday": "thursday",
    "temp": 15,
    "meta": "rain • Vind 2 m/s",
    "symbol_code": "rain"
  },
  "week": [
    {
      "weekday": "thu",
      "night": 14,
      "day": 15,
      "symbol_code": "rain"
    },
    {
      "weekday": "fri",
      "night": 13,
      "day": 19,
      "symbol_code": "partlycloudy_day"
    },
    {
      "weekday": "sat",
      "night": 11,
      "day": 19,
      "symbol_code": "clearsky_day"
    },
    {
      "weekday": "sun",
      "night": 10,
      "day": 20,
      "symbol_code": "rain"
    },
    {
      "weekday": "mon",
      "night": 14,
      "day": 19,
      "symbol_code": "cloudy"
    },
    {
      "weekday": "tue",
      "night": 14,
      "day": 17,
      "symbol_code": "rain"
    },
    {
      "weekday": "wed",
      "night": 12,
      "day": 17,
      "symbol_code": "rainshowers_day"
    }
  ]
}