{
  "updated": "2026-05-28 23:47 CEST",
  "today": {
    "weekday": "thursday",
    "temp": 11,
    "meta": "clearsky night • Vind 1 m/s",
    "symbol_code": "clearsky_night"
  },
  "week": [
    {
      "weekday": "thu",
      "night": 9,
      "day": 11,
      "symbol_code": "clearsky_night"
    },
    {
      "weekday": "fri",
      "night": 6,
      "day": 22,
      "symbol_code": "cloudy"
    },
    {
      "weekday": "sat",
      "night": 12,
      "day": 17,
      "symbol_code": "cloudy"
    },
    {
      "weekday": "sun",
      "night": 11,
      "day": 20,
      "symbol_code": "partlycloudy_day"
    },
    {
      "weekday": "mon",
      "night": 12,
      "day": 19,
      "symbol_code": "cloudy"
    },
    {
      "weekday": "tue",
      "night": 13,
      "day": 20,
      "symbol_code": "rain"
    },
    {
      "weekday": "wed",
      "night": 14,
      "day": 19,
      "symbol_code": "partlycloudy_day"
    }
  ]
}