{
  "updated": "2026-05-31 16:24 CEST",
  "today": {
    "weekday": "sunday",
    "temp": 20,
    "meta": "cloudy • Vind 3 m/s",
    "symbol_code": "cloudy"
  },
  "week": [
    {
      "weekday": "sun",
      "night": 14,
      "day": 20,
      "symbol_code": "cloudy"
    },
    {
      "weekday": "mon",
      "night": 12,
      "day": 18,
      "symbol_code": "partlycloudy_day"
    },
    {
      "weekday": "tue",
      "night": 11,
      "day": 21,
      "symbol_code": "cloudy"
    },
    {
      "weekday": "wed",
      "night": 16,
      "day": 24,
      "symbol_code": "rain"
    },
    {
      "weekday": "thu",
      "night": 15,
      "day": 20,
      "symbol_code": "cloudy"
    },
    {
      "weekday": "fri",
      "night": 15,
      "day": 20,
      "symbol_code": "partlycloudy_day"
    },
    {
      "weekday": "sat",
      "night": 13,
      "day": 19,
      "symbol_code": "cloudy"
    }
  ]
}