{
  "updated": "2026-05-14 01:45 CEST",
  "today": {
    "weekday": "thursday",
    "temp": 6,
    "meta": "rain • Vind 1 m/s",
    "symbol_code": "rain"
  },
  "week": [
    {
      "weekday": "wed",
      "night": 6,
      "day": 6,
      "symbol_code": "rain"
    },
    {
      "weekday": "thu",
      "night": 6,
      "day": 11,
      "symbol_code": "rain"
    },
    {
      "weekday": "fri",
      "night": 7,
      "day": 14,
      "symbol_code": "fair_day"
    },
    {
      "weekday": "sat",
      "night": 5,
      "day": 12,
      "symbol_code": "rain"
    },
    {
      "weekday": "sun",
      "night": 7,
      "day": 14,
      "symbol_code": "partlycloudy_day"
    },
    {
      "weekday": "mon",
      "night": 6,
      "day": 17,
      "symbol_code": "partlycloudy_day"
    },
    {
      "weekday": "tue",
      "night": 9,
      "day": 19,
      "symbol_code": "fair_day"
    }
  ]
}