{
  "updated": "2026-07-24 11:40 CEST",
  "today": {
    "weekday": "friday",
    "temp": 20,
    "meta": "partlycloudy day • Vind 5 m/s",
    "symbol_code": "partlycloudy_day"
  },
  "week": [
    {
      "weekday": "fri",
      "night": 16,
      "day": 20,
      "symbol_code": "partlycloudy_day"
    },
    {
      "weekday": "sat",
      "night": 15,
      "day": 18,
      "symbol_code": "cloudy"
    },
    {
      "weekday": "sun",
      "night": 15,
      "day": 19,
      "symbol_code": "cloudy"
    },
    {
      "weekday": "mon",
      "night": 14,
      "day": 19,
      "symbol_code": "fair_day"
    },
    {
      "weekday": "tue",
      "night": 15,
      "day": 20,
      "symbol_code": "fair_day"
    },
    {
      "weekday": "wed",
      "night": 17,
      "day": 23,
      "symbol_code": "partlycloudy_day"
    },
    {
      "weekday": "thu",
      "night": 17,
      "day": 24,
      "symbol_code": "partlycloudy_day"
    }
  ]
}